py3compat.py
setup.py
py3compat.egg-info/PKG-INFO
py3compat.egg-info/SOURCES.txt
py3compat.egg-info/dependency_links.txt
py3compat.egg-info/top_level.txt