Metadata-Version: 1.1
Name: py3compat
Version: 0.3
Summary: Small Python2/3 helpers to avoid depending on six.
Home-page: http://github.com/yeleman/py3compat
Author: yeleman
Author-email: rgaudin@gmail.com
License: UNKNOWN
Platform: UNKNOWN
Classifier: Development Status :: 4 - Beta
Classifier: Intended Audience :: Developers
Classifier: License :: OSI Approved :: BSD License
Classifier: Programming Language :: Python
Classifier: Programming Language :: Python :: 2.7
Classifier: Programming Language :: Python :: 3.3
